bam_core/__init__.py
bam_core/__version__.py
bam_core/function.py
bam_core/settings.py
bam_core/lib/__init__.py
bam_core/lib/airtable.py
bam_core/lib/listmonk.py
bam_core/lib/s3.py
bam_core/utils/__init__.py
bam_core/utils/etc.py
bam_core/utils/phone.py
bam_core/utils/serde.py
tests/__init__.py
tests/test_security.py
tests/test_serde.py
bam_core-2023.4.30.1682823805.dist-info/METADATA
bam_core-2023.4.30.1682823805.dist-info/WHEEL
bam_core-2023.4.30.1682823805.dist-info/top_level.txt
bam_core-2023.4.30.1682823805.dist-info/RECORD
